tektii_sdk/__init__.py
tektii_sdk/__version__.py
tektii_sdk/cli.py
tektii_sdk/collector.py
tektii_sdk/config.py
tektii_sdk/exceptions.py
tektii_sdk/push.py
tektii_sdk/py.typed
tektii_sdk/server.py
tektii_sdk/strategy.py
tektii_sdk/validator.py
tektii_sdk/apis/__init__.py
tektii_sdk/apis/base.py
tektii_sdk/apis/ib.py
tektii_sdk/apis/mt4.py
tektii_sdk/proto/__init__.py
tektii_sdk/proto/strategy_pb2.py
tektii_sdk/proto/strategy_pb2_grpc.py
tektii_strategy_sdk-0.6.0.dist-info/licenses/LICENSE.md
tektii_strategy_sdk-0.6.0.dist-info/METADATA
tektii_strategy_sdk-0.6.0.dist-info/WHEEL
tektii_strategy_sdk-0.6.0.dist-info/entry_points.txt
tektii_strategy_sdk-0.6.0.dist-info/top_level.txt
tektii_strategy_sdk-0.6.0.dist-info/RECORD
