Metadata-Version: 2.4
Name: tektii-strategy-sdk
Version: 0.6.0
Summary: SDK for building and running backtest strategies on the Tektii platform.
Author-email: Tektii Team <support@tektii.com>
Maintainer-email: Tektii Team <support@tektii.com>
License: MIT
Project-URL: Homepage, https://github.com/tektii/tektii-strategy-sdk-python
Project-URL: Documentation, https://docs.tektii.com
Project-URL: Repository, https://github.com/tektii/tektii-strategy-sdk-python
Project-URL: Issues, https://github.com/tektii/tektii-strategy-sdk-python/issues
Project-URL: Changelog, https://github.com/tektii/tektii-strategy-sdk-python/blob/main/CHANGELOG.md
Keywords: trading,backtesting,strategy,quantitative-finance,algorithmic-trading,grpc,simulation
Classifier: Development Status :: 4 - Beta
Classifier: Intended Audience :: Developers
Classifier: Intended Audience :: Financial and Insurance Industry
Classifier: Topic :: Office/Business :: Financial :: Investment
Classifier: License :: OSI Approved :: MIT License
Classifier: Programming Language :: Python :: 3
Classifier: Programming Language :: Python :: 3.8
Classifier: Programming Language :: Python :: 3.9
Classifier: Programming Language :: Python :: 3.10
Classifier: Programming Language :: Python :: 3.11
Classifier: Operating System :: OS Independent
Classifier: Typing :: Typed
Requires-Python: >=3.8
License-File: LICENSE.md
Requires-Dist: grpcio>=1.50.0
Requires-Dist: grpcio-tools>=1.50.0
Requires-Dist: grpcio-reflection>=1.50.0
Requires-Dist: grpcio-health-checking>=1.50.0
Requires-Dist: protobuf>=4.21.0
Requires-Dist: pydantic>=2.0.0
Requires-Dist: pydantic-settings>=2.0.0
Requires-Dist: python-dateutil>=2.8.2
Requires-Dist: numpy>=1.21.0
Requires-Dist: pandas>=1.3.0
Requires-Dist: requests>=2.28.0
Provides-Extra: dev
Requires-Dist: pytest>=7.0.0; extra == "dev"
Requires-Dist: pytest-asyncio>=0.21.0; extra == "dev"
Requires-Dist: pytest-cov>=4.0.0; extra == "dev"
Requires-Dist: pytest-mock>=3.10.0; extra == "dev"
Requires-Dist: black>=23.0.0; extra == "dev"
Requires-Dist: isort>=5.11.0; extra == "dev"
Requires-Dist: flake8>=6.0.0; extra == "dev"
Requires-Dist: mypy>=1.0.0; extra == "dev"
Requires-Dist: pylint>=2.16.0; extra == "dev"
Requires-Dist: pre-commit>=3.0.0; extra == "dev"
Requires-Dist: ipython>=8.0.0; extra == "dev"
Requires-Dist: ipdb>=0.13.0; extra == "dev"
Requires-Dist: requests>=2.32.0; extra == "dev"
Requires-Dist: types-requests>=2.28.0; extra == "dev"
Requires-Dist: build>=0.10.0; extra == "dev"
Requires-Dist: twine>=4.0.0; extra == "dev"
Requires-Dist: wheel>=0.38.0; extra == "dev"
Provides-Extra: examples
Requires-Dist: ta>=0.10.0; extra == "examples"
Dynamic: license-file
